{
  "app_inv_norm": 0.0000483359426207124,
  "diag_ae_mean": 1.6558814652702775e-7,
  "skel_ae": 0.000034323808813142224,
  "tot_num_samples": 694,
  "total_elapsed_time": 6,
  "extraction_time": 620,
  "residual_size": 316,
  "sampling_time": [
    39,
    206
  ],
  "id_times": [
    {
      "nullification": 25,
      "id": 0
    },
    {
      "nullification": 12,
      "id": 0
    },
    {
      "nullification": 13,
      "id": 0
    },
    {
      "nullification": 14,
      "id": 0
    },
    {
      "nullification": 16,
      "id": 0
    },
    {
      "nullification": 16,
      "id": 0
    },
    {
      "nullification": 18,
      "id": 0
    },
    {
      "nullification": 21,
      "id": 0
    },
    {
      "nullification": 38,
      "id": 0
    },
    {
      "nullification": 29,
      "id": 0
    },
    {
      "nullification": 31,
      "id": 0
    },
    {
      "nullification": 30,
      "id": 0
    },
    {
      "nullification": 33,
      "id": 0
    },
    {
      "nullification": 30,
      "id": 0
    },
    {
      "nullification": 34,
      "id": 0
    },
    {
      "nullification": 33,
      "id": 0
    },
    {
      "nullification": 34,
      "id": 0
    },
    {
      "nullification": 34,
      "id": 0
    },
    {
      "nullification": 35,
      "id": 0
    },
    {
      "nullification": 38,
      "id": 0
    },
    {
      "nullification": 38,
      "id": 0
    },
    {
      "nullification": 38,
      "id": 0
    },
    {
      "nullification": 40,
      "id": 0
    },
    {
      "nullification": 40,
      "id": 0
    },
    {
      "nullification": 41,
      "id": 0
    },
    {
      "nullification": 40,
      "id": 0
    },
    {
      "nullification": 42,
      "id": 0
    },
    {
      "nullification": 43,
      "id": 0
    },
    {
      "nullification": 43,
      "id": 0
    },
    {
      "nullification": 43,
      "id": 0
    },
    {
      "nullification": 45,
      "id": 0
    },
    {
      "nullification": 49,
      "id": 0
    },
    {
      "nullification": 62,
      "id": 0
    },
    {
      "nullification": 64,
      "id": 0
    },
    {
      "nullification": 66,
      "id": 0
    },
    {
      "nullification": 69,
      "id": 0
    },
    {
      "nullification": 72,
      "id": 0
    },
    {
      "nullification": 68,
      "id": 0
    },
    {
      "nullification": 71,
      "id": 0
    },
    {
      "nullification": 75,
      "id": 0
    },
    {
      "nullification": 80,
      "id": 0
    },
    {
      "nullification": 79,
      "id": 0
    },
    {
      "nullification": 78,
      "id": 0
    },
    {
      "nullification": 77,
      "id": 0
    },
    {
      "nullification": 80,
      "id": 0
    },
    {
      "nullification": 83,
      "id": 0
    },
    {
      "nullification": 86,
      "id": 0
    },
    {
      "nullification": 84,
      "id": 0
    },
    {
      "nullification": 83,
      "id": 0
    },
    {
      "nullification": 85,
      "id": 0
    },
    {
      "nullification": 81,
      "id": 0
    },
    {
      "nullification": 82,
      "id": 0
    },
    {
      "nullification": 92,
      "id": 0
    },
    {
      "nullification": 90,
      "id": 0
    },
    {
      "nullification": 96,
      "id": 0
    },
    {
      "nullification": 93,
      "id": 0
    }
  ],
  "lu_times": [
    {
      "io": 0,
      "extraction": 17,
      "assembly": 0
    },
    {
      "io": 0,
      "extraction": 18,
      "assembly": 0
    },
    {
      "io": 0,
      "extraction": 20,
      "assembly": 0
    },
    {
      "io": 0,
      "extraction": 32,
      "assembly": 0
    },
    {
      "io": 0,
      "extraction": 31,
      "assembly": 0
    },
    {
      "io": 0,
      "extraction": 33,
      "assembly": 0
    },
    {
      "io": 0,
      "extraction": 33,
      "assembly": 0
    },
    {
      "io": 0,
      "extraction": 35,
      "assembly": 0
    },
    {
      "io": 0,
      "extraction": 31,
      "assembly": 0
    },
    {
      "io": 0,
      "extraction": 40,
      "assembly": 0
    },
    {
      "io": 0,
      "extraction": 36,
      "assembly": 0
    },
    {
      "io": 0,
      "extraction": 34,
      "assembly": 0
    },
    {
      "io": 0,
      "extraction": 39,
      "assembly": 0
    },
    {
      "io": 0,
      "extraction": 37,
      "assembly": 0
    },
    {
      "io": 0,
      "extraction": 42,
      "assembly": 0
    },
    {
      "io": 0,
      "extraction": 42,
      "assembly": 0
    },
    {
      "io": 0,
      "extraction": 41,
      "assembly": 0
    },
    {
      "io": 0,
      "extraction": 42,
      "assembly": 0
    },
    {
      "io": 0,
      "extraction": 42,
      "assembly": 0
    },
    {
      "io": 0,
      "extraction": 44,
      "assembly": 0
    },
    {
      "io": 0,
      "extraction": 43,
      "assembly": 0
    },
    {
      "io": 0,
      "extraction": 43,
      "assembly": 2
    },
    {
      "io": 0,
      "extraction": 57,
      "assembly": 0
    },
    {
      "io": 0,
      "extraction": 60,
      "assembly": 0
    },
    {
      "io": 0,
      "extraction": 46,
      "assembly": 0
    },
    {
      "io": 0,
      "extraction": 60,
      "assembly": 0
    },
    {
      "io": 0,
      "extraction": 52,
      "assembly": 0
    },
    {
      "io": 0,
      "extraction": 65,
      "assembly": 0
    },
    {
      "io": 0,
      "extraction": 75,
      "assembly": 0
    },
    {
      "io": 0,
      "extraction": 75,
      "assembly": 0
    },
    {
      "io": 0,
      "extraction": 70,
      "assembly": 0
    },
    {
      "io": 0,
      "extraction": 76,
      "assembly": 0
    },
    {
      "io": 0,
      "extraction": 79,
      "assembly": 0
    },
    {
      "io": 0,
      "extraction": 77,
      "assembly": 0
    },
    {
      "io": 0,
      "extraction": 85,
      "assembly": 0
    },
    {
      "io": 0,
      "extraction": 81,
      "assembly": 0
    },
    {
      "io": 0,
      "extraction": 84,
      "assembly": 0
    },
    {
      "io": 0,
      "extraction": 82,
      "assembly": 0
    },
    {
      "io": 0,
      "extraction": 84,
      "assembly": 0
    },
    {
      "io": 0,
      "extraction": 83,
      "assembly": 0
    },
    {
      "io": 0,
      "extraction": 82,
      "assembly": 0
    },
    {
      "io": 0,
      "extraction": 86,
      "assembly": 0
    },
    {
      "io": 0,
      "extraction": 85,
      "assembly": 0
    },
    {
      "io": 0,
      "extraction": 86,
      "assembly": 0
    },
    {
      "io": 0,
      "extraction": 89,
      "assembly": 0
    },
    {
      "io": 0,
      "extraction": 93,
      "assembly": 0
    },
    {
      "io": 0,
      "extraction": 94,
      "assembly": 0
    },
    {
      "io": 0,
      "extraction": 91,
      "assembly": 0
    }
  ],
  "update_times": [
    {
      "id": 0,
      "lu": 1
    },
    {
      "id": 0,
      "lu": 1
    },
    {
      "id": 0,
      "lu": 2
    },
    {
      "id": 0,
      "lu": 1
    },
    {
      "id": 0,
      "lu": 2
    },
    {
      "id": 0,
      "lu": 2
    },
    {
      "id": 0,
      "lu": 2
    },
    {
      "id": 0,
      "lu": 2
    },
    {
      "id": 0,
      "lu": 1
    },
    {
      "id": 0,
      "lu": 2
    },
    {
      "id": 0,
      "lu": 2
    },
    {
      "id": 0,
      "lu": 1
    },
    {
      "id": 0,
      "lu": 2
    },
    {
      "id": 0,
      "lu": 2
    },
    {
      "id": 0,
      "lu": 2
    },
    {
      "id": 0,
      "lu": 2
    },
    {
      "id": 0,
      "lu": 2
    },
    {
      "id": 0,
      "lu": 2
    },
    {
      "id": 0,
      "lu": 2
    },
    {
      "id": 0,
      "lu": 2
    },
    {
      "id": 0,
      "lu": 2
    },
    {
      "id": 0,
      "lu": 25
    },
    {
      "id": 0,
      "lu": 1
    },
    {
      "id": 0,
      "lu": 2
    },
    {
      "id": 0,
      "lu": 2
    },
    {
      "id": 0,
      "lu": 3
    },
    {
      "id": 0,
      "lu": 2
    },
    {
      "id": 0,
      "lu": 2
    },
    {
      "id": 0,
      "lu": 2
    },
    {
      "id": 0,
      "lu": 2
    },
    {
      "id": 0,
      "lu": 2
    },
    {
      "id": 0,
      "lu": 2
    },
    {
      "id": 0,
      "lu": 2
    },
    {
      "id": 0,
      "lu": 2
    },
    {
      "id": 0,
      "lu": 2
    },
    {
      "id": 0,
      "lu": 2
    },
    {
      "id": 0,
      "lu": 2
    },
    {
      "id": 0,
      "lu": 2
    },
    {
      "id": 0,
      "lu": 2
    },
    {
      "id": 0,
      "lu": 2
    },
    {
      "id": 0,
      "lu": 2
    },
    {
      "id": 0,
      "lu": 2
    },
    {
      "id": 0,
      "lu": 2
    },
    {
      "id": 0,
      "lu": 2
    },
    {
      "id": 0,
      "lu": 3
    },
    {
      "id": 0,
      "lu": 3
    },
    {
      "id": 0,
      "lu": 2
    },
    {
      "id": 0,
      "lu": 2
    }
  ]
}